README
setup.py
aipsetup.egg-info/PKG-INFO
aipsetup.egg-info/SOURCES.txt
aipsetup.egg-info/dependency_links.txt
aipsetup.egg-info/entry_points.txt
aipsetup.egg-info/requires.txt
aipsetup.egg-info/top_level.txt
wayround_org/aipsetup/__init__.py
wayround_org/aipsetup/bootimage.py
wayround_org/aipsetup/build.py
wayround_org/aipsetup/client_pkg.py
wayround_org/aipsetup/client_src.py
wayround_org/aipsetup/commands.py
wayround_org/aipsetup/commands_local_build.py
wayround_org/aipsetup/commands_local_sys.py
wayround_org/aipsetup/commands_pkg_client.py
wayround_org/aipsetup/commands_pkg_server.py
wayround_org/aipsetup/commands_src_client.py
wayround_org/aipsetup/commands_src_server.py
wayround_org/aipsetup/config.py
wayround_org/aipsetup/controllers.py
wayround_org/aipsetup/dbconnections.py
wayround_org/aipsetup/dependencies.py
wayround_org/aipsetup/docbook.py
wayround_org/aipsetup/get_list_procs.py
wayround_org/aipsetup/gtk.py
wayround_org/aipsetup/host_arch_params.py
wayround_org/aipsetup/info.py
wayround_org/aipsetup/infoeditor.py
wayround_org/aipsetup/main.py
wayround_org/aipsetup/package.py
wayround_org/aipsetup/package_name_parser.py
wayround_org/aipsetup/repository.py
wayround_org/aipsetup/server_pkg.py
wayround_org/aipsetup/server_pkg_ui.py
wayround_org/aipsetup/server_src.py
wayround_org/aipsetup/system.py
wayround_org/aipsetup/sysupdates.py
wayround_org/aipsetup/sysuser.py
wayround_org/aipsetup/version.py
wayround_org/aipsetup/builder_scripts/Cg.py
wayround_org/aipsetup/builder_scripts/ConsoleKit.py
wayround_org/aipsetup/builder_scripts/FreeImage.py
wayround_org/aipsetup/builder_scripts/ModemManager.py
wayround_org/aipsetup/builder_scripts/NetworkManager.py
wayround_org/aipsetup/builder_scripts/SDL.py
wayround_org/aipsetup/builder_scripts/SDL2.py
wayround_org/aipsetup/builder_scripts/__init__.py
wayround_org/aipsetup/builder_scripts/a52dec.py
wayround_org/aipsetup/builder_scripts/acpid.py
wayround_org/aipsetup/builder_scripts/alsa_lib.py
wayround_org/aipsetup/builder_scripts/apache_ant.py
wayround_org/aipsetup/builder_scripts/apr.py
wayround_org/aipsetup/builder_scripts/apr_util.py
wayround_org/aipsetup/builder_scripts/aria2.py
