Metadata-Version: 1.0
Name: aipsetup
Version: 3.4.3
Summary: software tools for building and maintaining own gnu+linux distro
Home-page: https://github.com/AnimusPEXUS/wayround_org_aipsetup
Author: Alexey V Gorshkov
Author-email: animus@wayround.org
License: UNKNOWN
Platform: UNKNOWN
